broprompt/__init__.py
broprompt/context.py
broprompt/prompt_engineering.py
broprompt/tools.py
broprompt-0.1.5.dist-info/licenses/LICENSE
broprompt-0.1.5.dist-info/METADATA
broprompt-0.1.5.dist-info/WHEEL
broprompt-0.1.5.dist-info/top_level.txt
broprompt-0.1.5.dist-info/RECORD
