Metadata-Version: 2.4
Name: broprompt
Version: 0.1.5
Summary: Add your description here
Requires-Python: >=3.11
License-File: LICENSE
Requires-Dist: pyyaml>=6.0.2
Dynamic: license-file
